<?xml version="1.0" encoding="UTF-8" standalone="no"?>
<IP xmlns="http://mcd.rou.st.com/modules.php?name=mcu" DBVersion="V4.0" IPType="Thirdparty" IpGroup="Additional Software" Name="STMicroelectronics.X-CUBE-TOF1" Version="3.3.0" xmlns:ns0="http://www.w3.org/2001/XMLSchema-instance" ns0:schemaLocation="http://mcd.rou.st.com/modules.php?name=mcu ../../../../../../../doc/V4/Development/Specifications/db/IP_Modes.xsd">
    <!--Generated by CubeMX-->
    <RefMode Abstract="true" Name="BoardOoExtensionJj53L3A2">
        <ConfigForMode>BoardOoExtensionJj53L3A2</ConfigForMode>
        <Parameter Name="BoardOoExtensionJj53L3A2"/>
        <BspDependency Api="BSP_BUS_DRIVER" BspIpName="I2C" BspModeName="I2C" Comment="The I2C is used to exchange data with the sensor" GroupName="BSP" Name="53L3A2 BUS IO driver">
            <Condition Diagnostic="" Expression="SEMBoardOoExtensionJj53L3A2" Name="Condition_53L3A2_Board_Extension"/>
        </BspDependency>
        <BspDependency BspIpName="GPIO" BspModeName="EXTI" Comment="ToF sensor interrupt pin" GroupName="Application" Name="TOF_INT_PIN">
            <Condition Diagnostic="" Expression="SEMTOF1IiApplicationsCcDeviceJjApplicationJj53L3A2IiSimpleRanging" Name="Condition_53L3A2_INT_PIN"/>
        </BspDependency>
    </RefMode>
    <RefMode Abstract="true" Name="BoardOoExtensionJj53L5A1">
        <ConfigForMode>BoardOoExtensionJj53L5A1</ConfigForMode>
        <Parameter Name="BoardOoExtensionJj53L5A1"/>
        <BspDependency Api="BSP_BUS_DRIVER" BspIpName="I2C" BspModeName="I2C" Comment="The I2C is used to exchange data with the sensor" GroupName="BSP" Name="53L5A1 BUS IO driver">
            <Condition Diagnostic="" Expression="SEMBoardOoExtensionJj53L5A1" Name="Condition_53L5A1_Board_Extension"/>
        </BspDependency>
        <BspDependency BspIpName="GPIO" BspModeName="EXTI" Comment="ToF sensor interrupt pin" GroupName="Application" Name="TOF_INT_PIN">
            <Condition Diagnostic="" Expression="SEMTOF1IiApplicationsCcDeviceJjApplicationJj53L5A1IiSimpleRanging | SEMTOF1IiApplicationsCcDeviceJjApplicationJj53L5A1IiThresholdDetection" Name="Condition_53L5A1_INT_PIN"/>
        </BspDependency>
        <BspDependency BspIpName="GPIO" BspModeName="Output" Comment="Power enable pin for left satellite module" GroupName="Application" Name="53L5A1_PWR_EN_L">
            <Condition Diagnostic="" Expression="SEMTOF1IiApplicationsCcDeviceJjApplicationJj53L5A1IiMultiSensorRanging" Name="Condition_53L5A1_MultiSensorRanging_Application"/>
        </BspDependency>
        <BspDependency BspIpName="GPIO" BspModeName="Output" Comment="Power enable pin for right satellite module" GroupName="Application" Name="53L5A1_PWR_EN_R">
            <Condition Diagnostic="" Expression="SEMTOF1IiApplicationsCcDeviceJjApplicationJj53L5A1IiMultiSensorRanging" Name="Condition_53L5A1_MultiSensorRanging_Application"/>
        </BspDependency>
        <BspDependency BspIpName="GPIO" BspModeName="Output" Comment="Power enable pin for center on-board module" GroupName="Application" Name="53L5A1_PWR_EN_C">
            <Condition Diagnostic="" Expression="SEMTOF1IiApplicationsCcDeviceJjApplicationJj53L5A1IiSimpleRanging | SEMTOF1IiApplicationsCcDeviceJjApplicationJj53L5A1IiMultiSensorRanging | SEMTOF1IiApplicationsCcDeviceJjApplicationJj53L5A1IiThresholdDetection" Name="Condition_53L5A1_Application"/>
        </BspDependency>
        <BspDependency BspIpName="GPIO" BspModeName="Output" Comment="Low Power pin for left satellite module" GroupName="Application" Name="53L5A1_LPn_L">
            <Condition Diagnostic="" Expression="SEMTOF1IiApplicationsCcDeviceJjApplicationJj53L5A1IiMultiSensorRanging" Name="Condition_53L5A1_MultiSensorRanging_Application"/>
        </BspDependency>
        <BspDependency BspIpName="GPIO" BspModeName="Output" Comment="Low Power pin for right satellite module" GroupName="Application" Name="53L5A1_LPn_R">
            <Condition Diagnostic="" Expression="SEMTOF1IiApplicationsCcDeviceJjApplicationJj53L5A1IiMultiSensorRanging" Name="Condition_53L5A1_MultiSensorRanging_Application"/>
        </BspDependency>
        <BspDependency BspIpName="GPIO" BspModeName="Output" Comment="Low Power pin for center on-board module" GroupName="Application" Name="53L5A1_LPn_C">
            <Condition Diagnostic="" Expression="SEMTOF1IiApplicationsCcDeviceJjApplicationJj53L5A1IiSimpleRanging | SEMTOF1IiApplicationsCcDeviceJjApplicationJj53L5A1IiMultiSensorRanging | SEMTOF1IiApplicationsCcDeviceJjApplicationJj53L5A1IiThresholdDetection" Name="Condition_53L5A1_Application"/>
        </BspDependency>
        <BspDependency BspIpName="GPIO" BspModeName="Output" Comment="I2C reset pin for left satellite module" GroupName="Application" Name="53L5A1_I2C_RST_L">
            <Condition Diagnostic="" Expression="SEMTOF1IiApplicationsCcDeviceJjApplicationJj53L5A1IiMultiSensorRanging" Name="Condition_53L5A1_MultiSensorRanging_Application"/>
        </BspDependency>
        <BspDependency BspIpName="GPIO" BspModeName="Output" Comment="I2C reset pin for right satellite module" GroupName="Application" Name="53L5A1_I2C_RST_R">
            <Condition Diagnostic="" Expression="SEMTOF1IiApplicationsCcDeviceJjApplicationJj53L5A1IiMultiSensorRanging" Name="Condition_53L5A1_MultiSensorRanging_Application"/>
        </BspDependency>
        <BspDependency BspIpName="GPIO" BspModeName="Output" Comment="I2C reset pin for center on-board module" GroupName="Application" Name="53L5A1_I2C_RST_C">
            <Condition Diagnostic="" Expression="SEMTOF1IiApplicationsCcDeviceJjApplicationJj53L5A1IiSimpleRanging | SEMTOF1IiApplicationsCcDeviceJjApplicationJj53L5A1IiMultiSensorRanging | SEMTOF1IiApplicationsCcDeviceJjApplicationJj53L5A1IiThresholdDetection" Name="Condition_53L5A1_Application"/>
        </BspDependency>
    </RefMode>
    <RefMode Abstract="true" Name="BoardOoExtensionJj53L7A1">
        <ConfigForMode>BoardOoExtensionJj53L7A1</ConfigForMode>
        <Parameter Name="BoardOoExtensionJj53L7A1"/>
        <BspDependency Api="BSP_BUS_DRIVER" BspIpName="I2C" BspModeName="I2C" Comment="The I2C is used to exchange data with the sensor" GroupName="BSP" Name="53L7A1 BUS IO driver">
            <Condition Diagnostic="" Expression="SEMBoardOoExtensionJj53L7A1" Name="Condition_53L7A1_Board_Extension"/>
        </BspDependency>
        <BspDependency BspIpName="GPIO" BspModeName="EXTI" Comment="ToF sensor interrupt pin" GroupName="Application" Name="TOF_INT_PIN">
            <Condition Diagnostic="" Expression="SEMTOF1IiApplicationsCcDeviceJjApplicationJj53L7A1IiSimpleRanging | SEMTOF1IiApplicationsCcDeviceJjApplicationJj53L7A1IiThresholdDetection" Name="Condition_53L7A1_INT_PIN"/>
        </BspDependency>
        <BspDependency BspIpName="GPIO" BspModeName="Output" Comment="Power enable pin for left satellite module" GroupName="Application" Name="53L7A1_PWR_EN_L">
            <Condition Diagnostic="" Expression="SEMTOF1IiApplicationsCcDeviceJjApplicationJj53L7A1IiMultiSensorRanging" Name="Condition_53L7A1_MultiSensorRanging_Application"/>
        </BspDependency>
        <BspDependency BspIpName="GPIO" BspModeName="Output" Comment="Power enable pin for right satellite module" GroupName="Application" Name="53L7A1_PWR_EN_R">
            <Condition Diagnostic="" Expression="SEMTOF1IiApplicationsCcDeviceJjApplicationJj53L7A1IiMultiSensorRanging" Name="Condition_53L7A1_MultiSensorRanging_Application"/>
        </BspDependency>
        <BspDependency BspIpName="GPIO" BspModeName="Output" Comment="Power enable pin for center on-board module" GroupName="Application" Name="53L7A1_PWR_EN_C">
            <Condition Diagnostic="" Expression="SEMTOF1IiApplicationsCcDeviceJjApplicationJj53L7A1IiSimpleRanging | SEMTOF1IiApplicationsCcDeviceJjApplicationJj53L7A1IiMultiSensorRanging | SEMTOF1IiApplicationsCcDeviceJjApplicationJj53L7A1IiThresholdDetection" Name="Condition_53L7A1_Application"/>
        </BspDependency>
        <BspDependency BspIpName="GPIO" BspModeName="Output" Comment="Low Power pin for left satellite module" GroupName="Application" Name="53L7A1_LPn_L">
            <Condition Diagnostic="" Expression="SEMTOF1IiApplicationsCcDeviceJjApplicationJj53L7A1IiMultiSensorRanging" Name="Condition_53L7A1_MultiSensorRanging_Application"/>
        </BspDependency>
        <BspDependency BspIpName="GPIO" BspModeName="Output" Comment="Low Power pin for right satellite module" GroupName="Application" Name="53L7A1_LPn_R">
            <Condition Diagnostic="" Expression="SEMTOF1IiApplicationsCcDeviceJjApplicationJj53L7A1IiMultiSensorRanging" Name="Condition_53L7A1_MultiSensorRanging_Application"/>
        </BspDependency>
        <BspDependency BspIpName="GPIO" BspModeName="Output" Comment="Low Power pin for center on-board module" GroupName="Application" Name="53L7A1_LPn_C">
            <Condition Diagnostic="" Expression="SEMTOF1IiApplicationsCcDeviceJjApplicationJj53L7A1IiSimpleRanging | SEMTOF1IiApplicationsCcDeviceJjApplicationJj53L7A1IiMultiSensorRanging | SEMTOF1IiApplicationsCcDeviceJjApplicationJj53L7A1IiThresholdDetection" Name="Condition_53L7A1_Application"/>
        </BspDependency>
        <BspDependency BspIpName="GPIO" BspModeName="Output" Comment="I2C reset pin for left satellite module" GroupName="Application" Name="53L7A1_I2C_RST_L">
            <Condition Diagnostic="" Expression="SEMTOF1IiApplicationsCcDeviceJjApplicationJj53L7A1IiMultiSensorRanging" Name="Condition_53L7A1_MultiSensorRanging_Application"/>
        </BspDependency>
        <BspDependency BspIpName="GPIO" BspModeName="Output" Comment="I2C reset pin for right satellite module" GroupName="Application" Name="53L7A1_I2C_RST_R">
            <Condition Diagnostic="" Expression="SEMTOF1IiApplicationsCcDeviceJjApplicationJj53L7A1IiMultiSensorRanging" Name="Condition_53L7A1_MultiSensorRanging_Application"/>
        </BspDependency>
        <BspDependency BspIpName="GPIO" BspModeName="Output" Comment="I2C reset pin for center on-board module" GroupName="Application" Name="53L7A1_I2C_RST_C">
            <Condition Diagnostic="" Expression="SEMTOF1IiApplicationsCcDeviceJjApplicationJj53L7A1IiSimpleRanging | SEMTOF1IiApplicationsCcDeviceJjApplicationJj53L7A1IiMultiSensorRanging | SEMTOF1IiApplicationsCcDeviceJjApplicationJj53L7A1IiThresholdDetection" Name="Condition_53L7A1_Application"/>
        </BspDependency>
    </RefMode>
    <RefMode Abstract="true" Name="BoardOoExtensionJj53L8A1">
        <ConfigForMode>BoardOoExtensionJj53L8A1</ConfigForMode>
        <Parameter Name="BoardOoExtensionJj53L8A1"/>
        <BspDependency Api="BSP_BUS_DRIVER" BspIpName="I2C" BspModeName="I2C" Comment="The I2C is used to exchange data with the sensor" GroupName="BSP" Name="53L8A1 BUS IO driver">
            <Condition Diagnostic="" Expression="SEMBoardOoExtensionJj53L8A1" Name="Condition_53L8A1_Board_Extension"/>
        </BspDependency>
        <BspDependency BspIpName="GPIO" BspModeName="EXTI" Comment="ToF sensor interrupt pin" GroupName="Application" Name="TOF_INT_PIN">
            <Condition Diagnostic="" Expression="SEMTOF1IiApplicationsCcDeviceJjApplicationJj53L8A1IiSimpleRanging | SEMTOF1IiApplicationsCcDeviceJjApplicationJj53L8A1IiThresholdDetection" Name="Condition_53L8A1_INT_PIN"/>
        </BspDependency>
        <BspDependency BspIpName="GPIO" BspModeName="Output" Comment="Power enable pin for center on-board module" GroupName="Application" Name="53L8A1_PWR_EN_C">
            <Condition Diagnostic="" Expression="SEMTOF1IiApplicationsCcDeviceJjApplicationJj53L8A1IiSimpleRanging | SEMTOF1IiApplicationsCcDeviceJjApplicationJj53L8A1IiThresholdDetection" Name="Condition_53L8A1_Application"/>
        </BspDependency>
        <BspDependency BspIpName="GPIO" BspModeName="Output" Comment="Low Power pin for center on-board module" GroupName="Application" Name="53L8A1_LPn_C">
            <Condition Diagnostic="" Expression="SEMTOF1IiApplicationsCcDeviceJjApplicationJj53L8A1IiSimpleRanging | SEMTOF1IiApplicationsCcDeviceJjApplicationJj53L8A1IiThresholdDetection" Name="Condition_53L8A1_Application"/>
        </BspDependency>
        <BspDependency BspIpName="GPIO" BspModeName="Output" Comment="I2C reset pin for center on-board module" GroupName="Application" Name="53L8A1_I2C_RST_C">
            <Condition Diagnostic="" Expression="SEMTOF1IiApplicationsCcDeviceJjApplicationJj53L8A1IiSimpleRanging | SEMTOF1IiApplicationsCcDeviceJjApplicationJj53L8A1IiThresholdDetection" Name="Condition_53L8A1_Application"/>
        </BspDependency>
    </RefMode>
    <RefMode Abstract="true" Name="BoardOoExtensionJj53L1A2">
        <ConfigForMode>BoardOoExtensionJj53L1A2</ConfigForMode>
        <Parameter Name="BoardOoExtensionJj53L1A2"/>
        <BspDependency Api="BSP_BUS_DRIVER" BspIpName="I2C" BspModeName="I2C" Comment="The I2C is used to exchange data with the sensor" GroupName="BSP" Name="53L1A2 BUS IO driver">
            <Condition Diagnostic="" Expression="SEMBoardOoExtensionJj53L1A2" Name="Condition_53L1A2_Board_Extension"/>
        </BspDependency>
        <BspDependency BspIpName="GPIO" BspModeName="EXTI" Comment="ToF sensor interrupt pin" GroupName="Application" Name="TOF_INT_PIN">
            <Condition Diagnostic="" Expression="SEMTOF1IiApplicationsCcDeviceJjApplicationJj53L1A2IiSimpleRanging" Name="Condition_53L1A2_INT_PIN"/>
        </BspDependency>
    </RefMode>
    <RefMode Abstract="true" Name="BoardOoExtensionJj53L4A2">
        <ConfigForMode>BoardOoExtensionJj53L4A2</ConfigForMode>
        <Parameter Name="BoardOoExtensionJj53L4A2"/>
        <BspDependency Api="BSP_BUS_DRIVER" BspIpName="I2C" BspModeName="I2C" Comment="The I2C is used to exchange data with the sensor" GroupName="BSP" Name="53L4A2 BUS IO driver">
            <Condition Diagnostic="" Expression="SEMBoardOoExtensionJj53L4A2" Name="Condition_53L4A2_Board_Extension"/>
        </BspDependency>
        <BspDependency BspIpName="GPIO" BspModeName="EXTI" Comment="ToF sensor interrupt pin" GroupName="Application" Name="TOF_INT_PIN">
            <Condition Diagnostic="" Expression="SEMTOF1IiApplicationsCcDeviceJjApplicationJj53L4A2IiSimpleRanging" Name="Condition_53L4A2_INT_PIN"/>
        </BspDependency>
        <BspDependency BspIpName="GPIO" BspModeName="Output" Comment="XSHUT pin for center on-board module" GroupName="Application" Name="53L4A2_XSHUT_C">
            <Condition Diagnostic="" Expression="SEMTOF1IiApplicationsCcDeviceJjApplicationJj53L4A2IiMultiSensorRanging | SEMTOF1IiApplicationsCcDeviceJjApplicationJj53L4A2IiSimpleRanging" Name="Condition_53L4A2_Application"/>
        </BspDependency>
        <BspDependency BspIpName="GPIO" BspModeName="Output" Comment="XSHUT pin for left on-board module" GroupName="Application" Name="53L4A2_XSHUT_L">
            <Condition Diagnostic="" Expression="SEMTOF1IiApplicationsCcDeviceJjApplicationJj53L4A2IiMultiSensorRanging" Name="Condition_53L4A2_MultiSensorRanging_Application"/>
        </BspDependency>
        <BspDependency BspIpName="GPIO" BspModeName="Output" Comment="XSHUT pin for right on-board module" GroupName="Application" Name="53L4A2_XSHUT_R">
            <Condition Diagnostic="" Expression="SEMTOF1IiApplicationsCcDeviceJjApplicationJj53L4A2IiMultiSensorRanging" Name="Condition_53L4A2_MultiSensorRanging_Application"/>
        </BspDependency>
    </RefMode>
    <RefMode Abstract="true" Name="BoardOoExtensionJj53L4A1">
        <ConfigForMode>BoardOoExtensionJj53L4A1</ConfigForMode>
        <Parameter Name="BoardOoExtensionJj53L4A1"/>
        <BspDependency Api="BSP_BUS_DRIVER" BspIpName="I2C" BspModeName="I2C" Comment="The I2C is used to exchange data with the sensor" GroupName="BSP" Name="53L4A1 BUS IO driver">
            <Condition Diagnostic="" Expression="SEMBoardOoExtensionJj53L4A1" Name="Condition_53L4A1_Board_Extension"/>
        </BspDependency>
        <BspDependency BspIpName="GPIO" BspModeName="EXTI" Comment="ToF sensor interrupt pin" GroupName="Application" Name="TOF_INT_PIN">
            <Condition Diagnostic="" Expression="SEMTOF1IiApplicationsCcDeviceJjApplicationJj53L4A1IiSimpleRanging | SEMTOF1IiApplicationsCcDeviceJjApplicationJj53L4A1IiThresholdDetection" Name="Condition_53L4A1_INT_PIN"/>
        </BspDependency>
        <BspDependency BspIpName="GPIO" BspModeName="Output" Comment="XSHUT pin for center on-board module" GroupName="Application" Name="53L4A1_XSHUT_C">
            <Condition Diagnostic="" Expression="SEMTOF1IiApplicationsCcDeviceJjApplicationJj53L4A1IiMultiSensorRanging | SEMTOF1IiApplicationsCcDeviceJjApplicationJj53L4A1IiSimpleRanging | SEMTOF1IiApplicationsCcDeviceJjApplicationJj53L4A1IiThresholdDetection" Name="Condition_53L4A1_Application"/>
        </BspDependency>
        <BspDependency BspIpName="GPIO" BspModeName="Output" Comment="XSHUT pin for left on-board module" GroupName="Application" Name="53L4A1_XSHUT_L">
            <Condition Diagnostic="" Expression="SEMTOF1IiApplicationsCcDeviceJjApplicationJj53L4A1IiMultiSensorRanging" Name="Condition_53L4A1_MultiSensorRanging_Application"/>
        </BspDependency>
        <BspDependency BspIpName="GPIO" BspModeName="Output" Comment="XSHUT pin for right on-board module" GroupName="Application" Name="53L4A1_XSHUT_R">
            <Condition Diagnostic="" Expression="SEMTOF1IiApplicationsCcDeviceJjApplicationJj53L4A1IiMultiSensorRanging" Name="Condition_53L4A1_MultiSensorRanging_Application"/>
        </BspDependency>
    </RefMode>
    <RefMode Abstract="true" Name="BoardOoPartJjRanging">
        <ConfigForMode>BoardOoPartJjRanging</ConfigForMode>
        <Parameter Name="BoardOoPartJjRangingJjVL53L3CX"/>
        <Parameter Name="BoardOoPartJjRangingJjVL53L5CX"/>
        <Parameter Name="BoardOoPartJjRangingJjVL53L7CX"/>
        <Parameter Name="BoardOoPartJjRangingJjVL53L8CX"/>
        <Parameter Name="BoardOoPartJjRangingJjVL53L1CB"/>
        <Parameter Name="BoardOoPartJjRangingJjVL53L4CX"/>
        <Parameter Name="BoardOoPartJjRangingJjVL53L4CD"/>
        <BspDependency Api="BSP_BUS_DRIVER" BspIpName="I2C" BspModeName="I2C" Comment="VL53L3CX I2C bus driver" GroupName="BSP" Name="VL53L3CX BUS IO driver">
            <Condition Diagnostic="" Expression="SEMBoardOoPartJjRangingJjVL53L3CX" Name="Condition_VL53L3CX_Board_Part"/>
        </BspDependency>
        <BspDependency BspIpName="GPIO" BspModeName="Output" Comment="VL53L3CX XSHUT pin" GroupName="Application" Name="VL53L3CX_XSHUT">
            <Condition Diagnostic="" Expression="SEMBoardOoPartJjRangingJjVL53L3CX" Name="Condition_VL53L3CX_Board_Part"/>
        </BspDependency>
        <BspDependency Api="BSP_BUS_DRIVER" BspIpName="I2C" BspModeName="I2C" Comment="VL53L4CX I2C bus driver" GroupName="BSP" Name="VL53L4CX BUS IO driver">
            <Condition Diagnostic="" Expression="SEMBoardOoPartJjRangingJjVL53L4CX" Name="Condition_VL53L4CX_Board_Part"/>
        </BspDependency>
        <BspDependency BspIpName="GPIO" BspModeName="Output" Comment="VL53L4CX XSHUT pin" GroupName="Application" Name="VL53L4CX_XSHUT">
            <Condition Diagnostic="" Expression="SEMBoardOoPartJjRangingJjVL53L4CX" Name="Condition_VL53L4CX_Board_Part"/>
        </BspDependency>
        <BspDependency Api="BSP_BUS_DRIVER" BspIpName="I2C" BspModeName="I2C" Comment="VL53L4CD I2C bus driver" GroupName="BSP" Name="VL53L4CD BUS IO driver">
            <Condition Diagnostic="" Expression="SEMBoardOoPartJjRangingJjVL53L4CD" Name="Condition_VL53L4CD_Board_Part"/>
        </BspDependency>
        <BspDependency BspIpName="GPIO" BspModeName="Output" Comment="VL53L4CD XSHUT pin" GroupName="Application" Name="VL53L4CD_XSHUT">
            <Condition Diagnostic="" Expression="SEMBoardOoPartJjRangingJjVL53L4CD" Name="Condition_VL53L4CD_Board_Part"/>
        </BspDependency>
        <BspDependency BspIpName="GPIO" BspModeName="EXTI" Comment="ToF sensor interrupt pin" GroupName="Application" Name="TOF_INT_PIN">
            <Condition Diagnostic="" Expression="SEMTOF1IiApplicationsCcDeviceJjApplicationJjVL53L4CDIiSimpleRanging | SEMTOF1IiApplicationsCcDeviceJjApplicationJjVL53L4CXIiSimpleRanging | SEMTOF1IiApplicationsCcDeviceJjApplicationJjVL53L3CXIiSimpleRanging | SEMTOF1IiApplicationsCcDeviceJjApplicationJjVL53L5CXIiSimpleRanging | SEMTOF1IiApplicationsCcDeviceJjApplicationJjVL53L7CXIiSimpleRanging | SEMTOF1IiApplicationsCcDeviceJjApplicationJjVL53L8CXIiSimpleRanging | SEMTOF1IiApplicationsCcDeviceJjApplicationJjVL53L1CBIiSimpleRanging" Name="Condition_Board_Part_Application"/>
        </BspDependency>
        <BspDependency Api="BSP_BUS_DRIVER" BspIpName="I2C" BspModeName="I2C" Comment="VL53L5CX I2C bus driver" GroupName="BSP" Name="VL53L5CX BUS IO driver">
            <Condition Diagnostic="" Expression="SEMBoardOoPartJjRangingJjVL53L5CX" Name="Condition_VL53L5CX_Board_Part"/>
        </BspDependency>
        <BspDependency BspIpName="GPIO" BspModeName="Output" Comment="VL53L5CX power enable pin" GroupName="Application" Name="VL53L5CX_PWR_EN">
            <Condition Diagnostic="" Expression="SEMBoardOoPartJjRangingJjVL53L5CX" Name="Condition_VL53L5CX_Board_Part"/>
        </BspDependency>
        <BspDependency BspIpName="GPIO" BspModeName="Output" Comment="VL53L5CX I2C reset pin" GroupName="Application" Name="VL53L5CX_I2C_RST">
            <Condition Diagnostic="" Expression="SEMBoardOoPartJjRangingJjVL53L5CX" Name="Condition_VL53L5CX_Board_Part"/>
        </BspDependency>
        <BspDependency BspIpName="GPIO" BspModeName="Output" Comment="VL53L5CX low power pin" GroupName="Application" Name="VL53L5CX_LPn">
            <Condition Diagnostic="" Expression="SEMBoardOoPartJjRangingJjVL53L5CX" Name="Condition_VL53L5CX_Board_Part"/>
        </BspDependency>
        <BspDependency Api="BSP_BUS_DRIVER" BspIpName="I2C" BspModeName="I2C" Comment="VL53L7CX I2C bus driver" GroupName="BSP" Name="VL53L7CX BUS IO driver">
            <Condition Diagnostic="" Expression="SEMBoardOoPartJjRangingJjVL53L7CX" Name="Condition_VL53L7CX_Board_Part"/>
        </BspDependency>
        <BspDependency BspIpName="GPIO" BspModeName="Output" Comment="VL53L7CX power enable pin" GroupName="Application" Name="VL53L7CX_PWR_EN">
            <Condition Diagnostic="" Expression="SEMBoardOoPartJjRangingJjVL53L7CX" Name="Condition_VL53L7CX_Board_Part"/>
        </BspDependency>
        <BspDependency BspIpName="GPIO" BspModeName="Output" Comment="VL53L7CX I2C reset pin" GroupName="Application" Name="VL53L7CX_I2C_RST">
            <Condition Diagnostic="" Expression="SEMBoardOoPartJjRangingJjVL53L7CX" Name="Condition_VL53L7CX_Board_Part"/>
        </BspDependency>
        <BspDependency BspIpName="GPIO" BspModeName="Output" Comment="VL53L7CX low power pin" GroupName="Application" Name="VL53L7CX_LPn">
            <Condition Diagnostic="" Expression="SEMBoardOoPartJjRangingJjVL53L7CX" Name="Condition_VL53L7CX_Board_Part"/>
        </BspDependency>
        <BspDependency Api="BSP_BUS_DRIVER" BspIpName="I2C" BspModeName="I2C" Comment="VL53L8CX I2C bus driver" GroupName="BSP" Name="VL53L8CX BUS IO driver">
            <Condition Diagnostic="" Expression="SEMBoardOoPartJjRangingJjVL53L8CX" Name="Condition_VL53L8CX_Board_Part"/>
        </BspDependency>
        <BspDependency BspIpName="GPIO" BspModeName="Output" Comment="VL53L8CX power enable pin" GroupName="Application" Name="VL53L8CX_PWR_EN">
            <Condition Diagnostic="" Expression="SEMBoardOoPartJjRangingJjVL53L8CX" Name="Condition_VL53L8CX_Board_Part"/>
        </BspDependency>
        <BspDependency BspIpName="GPIO" BspModeName="Output" Comment="VL53L8CX I2C reset pin" GroupName="Application" Name="VL53L8CX_I2C_RST">
            <Condition Diagnostic="" Expression="SEMBoardOoPartJjRangingJjVL53L8CX" Name="Condition_VL53L8CX_Board_Part"/>
        </BspDependency>
        <BspDependency BspIpName="GPIO" BspModeName="Output" Comment="VL53L8CX low power pin" GroupName="Application" Name="VL53L8CX_LPn">
            <Condition Diagnostic="" Expression="SEMBoardOoPartJjRangingJjVL53L8CX" Name="Condition_VL53L8CX_Board_Part"/>
        </BspDependency>
        <BspDependency Api="BSP_BUS_DRIVER" BspIpName="I2C" BspModeName="I2C" Comment="VL53L1CB I2C  bus driver" GroupName="BSP" Name="VL53L1CB BUS IO driver">
            <Condition Diagnostic="" Expression="SEMBoardOoPartJjRangingJjVL53L1CB" Name="Condition_VL53L1CB_Board_Part"/>
        </BspDependency>
        <BspDependency BspIpName="GPIO" BspModeName="Output" Comment="VL53L1CB XSHUT pin" GroupName="Application" Name="VL53L1CB_XSHUT">
            <Condition Diagnostic="" Expression="SEMBoardOoPartJjRangingJjVL53L1CB" Name="Condition_VL53L1CB_Board_Part"/>
        </BspDependency>
    </RefMode>
    <RefMode Abstract="true" Name="DeviceJjTOF1IiApplications">
        <ConfigForMode>DeviceJjTOF1IiApplications</ConfigForMode>
        <Parameter Name="TOF1IiApplicationsCcDeviceJjApplication"/>
        <Parameter Added="true" Name="TOF_RANGING_MODE">
            <Condition Diagnostic="" Expression="SEMTOF1IiApplicationsCcDeviceJjApplicationJj53L4A1IiSimpleRanging | SEMTOF1IiApplicationsCcDeviceJjApplicationJjVL53L4CDIiSimpleRanging | SEMTOF1IiApplicationsCcDeviceJjApplicationJj53L4A2IiSimpleRanging | SEMTOF1IiApplicationsCcDeviceJjApplicationJjVL53L4CXIiSimpleRanging | SEMTOF1IiApplicationsCcDeviceJjApplicationJj53L3A2IiSimpleRanging | SEMTOF1IiApplicationsCcDeviceJjApplicationJj53L5A1IiSimpleRanging | SEMTOF1IiApplicationsCcDeviceJjApplicationJj53L7A1IiSimpleRanging | SEMTOF1IiApplicationsCcDeviceJjApplicationJj53L8A1IiSimpleRanging | SEMTOF1IiApplicationsCcDeviceJjApplicationJjVL53L3CXIiSimpleRanging | SEMTOF1IiApplicationsCcDeviceJjApplicationJjVL53L5CXIiSimpleRanging | SEMTOF1IiApplicationsCcDeviceJjApplicationJjVL53L7CXIiSimpleRanging | SEMTOF1IiApplicationsCcDeviceJjApplicationJjVL53L8CXIiSimpleRanging | SEMTOF1IiApplicationsCcDeviceJjApplicationJj53L1A2IiSimpleRanging | SEMTOF1IiApplicationsCcDeviceJjApplicationJjVL53L1CBIiSimpleRanging" Name="Condition_RangingMode_Parameter"/>
        </Parameter>
        <Parameter Added="true" Name="TOF_OFFSET_CALIBRATION">
            <Condition Diagnostic="" Expression="SEMTOF1IiApplicationsCcDeviceJjApplicationJj53L4A1IiSimpleRanging | SEMTOF1IiApplicationsCcDeviceJjApplicationJj53L4A2IiSimpleRanging | SEMTOF1IiApplicationsCcDeviceJjApplicationJj53L3A2IiSimpleRanging | SEMTOF1IiApplicationsCcDeviceJjApplicationJj53L1A2IiSimpleRanging" Name="Condition_OffsetCalibration_Parameter"/>
        </Parameter>
        <Parameter Added="true" Name="TOF_XTALK_CALIBRATION">
            <Condition Diagnostic="" Expression="SEMTOF1IiApplicationsCcDeviceJjApplicationJj53L4A1IiSimpleRanging | SEMTOF1IiApplicationsCcDeviceJjApplicationJj53L4A2IiSimpleRanging | SEMTOF1IiApplicationsCcDeviceJjApplicationJj53L3A2IiSimpleRanging | SEMTOF1IiApplicationsCcDeviceJjApplicationJj53L5A1IiSimpleRanging | SEMTOF1IiApplicationsCcDeviceJjApplicationJj53L7A1IiSimpleRanging | SEMTOF1IiApplicationsCcDeviceJjApplicationJj53L8A1IiSimpleRanging | SEMTOF1IiApplicationsCcDeviceJjApplicationJj53L1A2IiSimpleRanging" Name="Condition_XtalkCalibration_Parameter"/>
        </Parameter>
        <BspDependency Api="BSP_COMMON_DRIVER" BspIpName="USART" BspModeName="Asynchronous" Comment="User USART" GroupName="BSP" Name="BSP USART"/>
        <BspDependency Api="BSP_COMMON_DRIVER" BspIpName="GPIO" BspModeName="EXTI" Comment="Get the state from user Button" GroupName="BSP" Name="BSP BUTTON">
            <Condition Diagnostic="" Expression="SEMTOF1IiApplicationsCcDeviceJjApplicationJj53L4A1IiSimpleRanging | SEMTOF1IiApplicationsCcDeviceJjApplicationJj53L4A2IiSimpleRanging | SEMTOF1IiApplicationsCcDeviceJjApplicationJj53L3A2IiSimpleRanging | SEMTOF1IiApplicationsCcDeviceJjApplicationJj53L5A1IiSimpleRanging | SEMTOF1IiApplicationsCcDeviceJjApplicationJj53L7A1IiSimpleRanging | SEMTOF1IiApplicationsCcDeviceJjApplicationJj53L8A1IiSimpleRanging | SEMTOF1IiApplicationsCcDeviceJjApplicationJj53L1A2IiSimpleRanging" Name="Condition_BSP_Button_Application"/>
        </BspDependency>
    </RefMode>
    <RefMode Abstract="true" Name="BoardOoSupportJjSTM32CubeIiCustomIiBSPIiDrivers">
        <ConfigForMode>BoardOoSupportJjSTM32CubeIiCustomIiBSPIiDrivers</ConfigForMode>
        <Parameter Name="STM32CubeIiCustomIiBSPIiDriversCcBoardOoSupportJjCustomJjRANGINGIiSENSOR"/>
    </RefMode>
    <ModeLogicOperator Name="OR">
        <Mode Name="BoardOoExtensionJj53L3A2">
            <ModeLogicOperator Name="OR">
                <Mode Name="BoardOoExtensionJj53L3A2">
                    <SignalLogicalOp Name="AND">
                        <Signal Name="VS_BoardOoExtensionJj53L3A2_2.0.3_3.3.0"/>
                    </SignalLogicalOp>
                </Mode>
            </ModeLogicOperator>
        </Mode>
        <Mode Name="BoardOoExtensionJj53L5A1">
            <ModeLogicOperator Name="OR">
                <Mode Name="BoardOoExtensionJj53L5A1">
                    <SignalLogicalOp Name="AND">
                        <Signal Name="VS_BoardOoExtensionJj53L5A1_1.0.5_3.3.0"/>
                    </SignalLogicalOp>
                </Mode>
            </ModeLogicOperator>
        </Mode>
        <Mode Name="BoardOoExtensionJj53L7A1">
            <ModeLogicOperator Name="OR">
                <Mode Name="BoardOoExtensionJj53L7A1">
                    <SignalLogicalOp Name="AND">
                        <Signal Name="VS_BoardOoExtensionJj53L7A1_1.0.1_3.3.0"/>
                    </SignalLogicalOp>
                </Mode>
            </ModeLogicOperator>
        </Mode>
        <Mode Name="BoardOoExtensionJj53L8A1">
            <ModeLogicOperator Name="OR">
                <Mode Name="BoardOoExtensionJj53L8A1">
                    <SignalLogicalOp Name="AND">
                        <Signal Name="VS_BoardOoExtensionJj53L8A1_1.0.0_3.3.0"/>
                    </SignalLogicalOp>
                </Mode>
            </ModeLogicOperator>
        </Mode>
        <Mode Name="BoardOoExtensionJj53L1A2">
            <ModeLogicOperator Name="OR">
                <Mode Name="BoardOoExtensionJj53L1A2">
                    <SignalLogicalOp Name="AND">
                        <Signal Name="VS_BoardOoExtensionJj53L1A2_1.0.2_3.3.0"/>
                    </SignalLogicalOp>
                </Mode>
            </ModeLogicOperator>
        </Mode>
        <Mode Name="BoardOoExtensionJj53L4A2">
            <ModeLogicOperator Name="OR">
                <Mode Name="BoardOoExtensionJj53L4A2">
                    <SignalLogicalOp Name="AND">
                        <Signal Name="VS_BoardOoExtensionJj53L4A2_1.0.2_3.3.0"/>
                    </SignalLogicalOp>
                </Mode>
            </ModeLogicOperator>
        </Mode>
        <Mode Name="BoardOoExtensionJj53L4A1">
            <ModeLogicOperator Name="OR">
                <Mode Name="BoardOoExtensionJj53L4A1">
                    <SignalLogicalOp Name="AND">
                        <Signal Name="VS_BoardOoExtensionJj53L4A1_1.0.2_3.3.0"/>
                    </SignalLogicalOp>
                </Mode>
            </ModeLogicOperator>
        </Mode>
        <Mode Name="BoardOoPartJjRanging">
            <ModeLogicOperator Name="OR">
                <Mode Name="BoardOoPartJjRanging">
                    <SignalLogicalOp Name="AND">
                        <Signal Name="VS_BoardOoPartJjRanging_2.0.3_3.3.0"/>
                    </SignalLogicalOp>
                </Mode>
            </ModeLogicOperator>
        </Mode>
        <Mode Name="DeviceJjTOF1IiApplications">
            <ModeLogicOperator Name="OR">
                <Mode Name="DeviceJjTOF1IiApplications">
                    <SignalLogicalOp Name="AND">
                        <Signal Name="VS_DeviceJjTOF1IiApplications_1.0.0_3.3.0"/>
                    </SignalLogicalOp>
                </Mode>
            </ModeLogicOperator>
        </Mode>
        <Mode Name="BoardOoSupportJjSTM32CubeIiCustomIiBSPIiDrivers">
            <ModeLogicOperator Name="OR">
                <Mode Name="BoardOoSupportJjSTM32CubeIiCustomIiBSPIiDrivers">
                    <SignalLogicalOp Name="AND">
                        <Signal Name="VS_BoardOoSupportJjSTM32CubeIiCustomIiBSPIiDrivers_1.0.0_3.3.0"/>
                    </SignalLogicalOp>
                </Mode>
            </ModeLogicOperator>
        </Mode>
    </ModeLogicOperator>
    <RefSignal Name="VS_BoardOoExtensionJj53L3A2_2.0.3_3.3.0" Virtual="true"/>
    <RefSignal Name="VS_BoardOoExtensionJj53L5A1_1.0.5_3.3.0" Virtual="true"/>
    <RefSignal Name="VS_BoardOoExtensionJj53L7A1_1.0.1_3.3.0" Virtual="true"/>
    <RefSignal Name="VS_BoardOoExtensionJj53L8A1_1.0.0_3.3.0" Virtual="true"/>
    <RefSignal Name="VS_BoardOoExtensionJj53L1A2_1.0.2_3.3.0" Virtual="true"/>
    <RefSignal Name="VS_BoardOoExtensionJj53L4A2_1.0.2_3.3.0" Virtual="true"/>
    <RefSignal Name="VS_BoardOoExtensionJj53L4A1_1.0.2_3.3.0" Virtual="true"/>
    <RefSignal Name="VS_BoardOoPartJjRanging_2.0.3_3.3.0" Virtual="true"/>
    <RefSignal Name="VS_BoardOoPartJjRanging_1.0.4_3.3.0" Virtual="true"/>
    <RefSignal Name="VS_BoardOoPartJjRanging_1.0.1_3.3.0" Virtual="true"/>
    <RefSignal Name="VS_BoardOoPartJjRanging_1.0.0_3.3.0" Virtual="true"/>
    <RefSignal Name="VS_BoardOoPartJjRanging_1.0.2_3.3.0" Virtual="true"/>
    <RefSignal Name="VS_DeviceJjTOF1IiApplications_1.0.0_3.3.0" Virtual="true"/>
    <RefSignal Name="VS_BoardOoSupportJjSTM32CubeIiCustomIiBSPIiDrivers_1.0.0_3.3.0" Virtual="true"/>
    <RefParameter Comment="X-NUCLEO-53L3A2 BSP drivers" DefaultValue="false" Group="Software component selection" Name="BoardOoExtensionJj53L3A2" TabName="BoardOoExtensionJj53L3A2" Type="boolean" Visible="false">
        <PossibleValue Comment="ENABLE" Semaphore="SEMBoardOoExtensionJj53L3A2" Value="true"/>
        <PossibleValue Comment="DISABLE" Value="false"/>
        <Condition Diagnostic="Cortex-M Device and board setup (X-NUCLEO-53L3A2)" Expression="CONDITIONIi53L3A2OoCondition=true"/>
    </RefParameter>
    <RefParameter Comment="X-NUCLEO-53L3A2 BSP drivers" DefaultValue="false" Group="Software component selection" Name="BoardOoExtensionJj53L3A2" TabName="BoardOoExtensionJj53L3A2" Type="boolean" Visible="false"/>
    <RefParameter Comment="X-NUCLEO-53L5A1 BSP drivers" DefaultValue="false" Group="Software component selection" Name="BoardOoExtensionJj53L5A1" TabName="BoardOoExtensionJj53L5A1" Type="boolean" Visible="false">
        <PossibleValue Comment="ENABLE" Semaphore="SEMBoardOoExtensionJj53L5A1" Value="true"/>
        <PossibleValue Comment="DISABLE" Value="false"/>
        <Condition Diagnostic="Cortex-M Device and board setup (X-NUCLEO-53L5A1)" Expression="CONDITIONIi53L5A1OoCondition=true"/>
    </RefParameter>
    <RefParameter Comment="X-NUCLEO-53L5A1 BSP drivers" DefaultValue="false" Group="Software component selection" Name="BoardOoExtensionJj53L5A1" TabName="BoardOoExtensionJj53L5A1" Type="boolean" Visible="false"/>
    <RefParameter Comment="X-NUCLEO-53L7A1 BSP drivers" DefaultValue="false" Group="Software component selection" Name="BoardOoExtensionJj53L7A1" TabName="BoardOoExtensionJj53L7A1" Type="boolean" Visible="false">
        <PossibleValue Comment="ENABLE" Semaphore="SEMBoardOoExtensionJj53L7A1" Value="true"/>
        <PossibleValue Comment="DISABLE" Value="false"/>
        <Condition Diagnostic="Cortex-M Device and board setup (X-NUCLEO-53L7A1)" Expression="CONDITIONIi53L7A1OoCondition=true"/>
    </RefParameter>
    <RefParameter Comment="X-NUCLEO-53L7A1 BSP drivers" DefaultValue="false" Group="Software component selection" Name="BoardOoExtensionJj53L7A1" TabName="BoardOoExtensionJj53L7A1" Type="boolean" Visible="false"/>
    <RefParameter Comment="X-NUCLEO-53L8A1 BSP drivers" DefaultValue="false" Group="Software component selection" Name="BoardOoExtensionJj53L8A1" TabName="BoardOoExtensionJj53L8A1" Type="boolean" Visible="false">
        <PossibleValue Comment="ENABLE" Semaphore="SEMBoardOoExtensionJj53L8A1" Value="true"/>
        <PossibleValue Comment="DISABLE" Value="false"/>
        <Condition Diagnostic="Cortex-M Device and board setup (X-NUCLEO-53L8A1)" Expression="CONDITIONIi53L8A1OoCondition=true"/>
    </RefParameter>
    <RefParameter Comment="X-NUCLEO-53L8A1 BSP drivers" DefaultValue="false" Group="Software component selection" Name="BoardOoExtensionJj53L8A1" TabName="BoardOoExtensionJj53L8A1" Type="boolean" Visible="false"/>
    <RefParameter Comment="X-NUCLEO-53L1A2 BSP drivers" DefaultValue="false" Group="Software component selection" Name="BoardOoExtensionJj53L1A2" TabName="BoardOoExtensionJj53L1A2" Type="boolean" Visible="false">
        <PossibleValue Comment="ENABLE" Semaphore="SEMBoardOoExtensionJj53L1A2" Value="true"/>
        <PossibleValue Comment="DISABLE" Value="false"/>
        <Condition Diagnostic="Cortex-M Device and board setup (X-NUCLEO-53L1A2)" Expression="CONDITIONIi53L1A2OoCondition=true"/>
    </RefParameter>
    <RefParameter Comment="X-NUCLEO-53L1A2 BSP drivers" DefaultValue="false" Group="Software component selection" Name="BoardOoExtensionJj53L1A2" TabName="BoardOoExtensionJj53L1A2" Type="boolean" Visible="false"/>
    <RefParameter Comment="X-NUCLEO-53L4A2 BSP drivers" DefaultValue="false" Group="Software component selection" Name="BoardOoExtensionJj53L4A2" TabName="BoardOoExtensionJj53L4A2" Type="boolean" Visible="false">
        <PossibleValue Comment="ENABLE" Semaphore="SEMBoardOoExtensionJj53L4A2" Value="true"/>
        <PossibleValue Comment="DISABLE" Value="false"/>
        <Condition Diagnostic="Cortex-M Device and board setup (X-NUCLEO-53L4A2)" Expression="CONDITIONIi53L4A2OoCondition=true"/>
    </RefParameter>
    <RefParameter Comment="X-NUCLEO-53L4A2 BSP drivers" DefaultValue="false" Group="Software component selection" Name="BoardOoExtensionJj53L4A2" TabName="BoardOoExtensionJj53L4A2" Type="boolean" Visible="false"/>
    <RefParameter Comment="X-NUCLEO-53L4A1 BSP drivers" DefaultValue="false" Group="Software component selection" Name="BoardOoExtensionJj53L4A1" TabName="BoardOoExtensionJj53L4A1" Type="boolean" Visible="false">
        <PossibleValue Comment="ENABLE" Semaphore="SEMBoardOoExtensionJj53L4A1" Value="true"/>
        <PossibleValue Comment="DISABLE" Value="false"/>
        <Condition Diagnostic="Cortex-M Device and board setup (X-NUCLEO-53L4A1)" Expression="CONDITIONIi53L4A1OoCondition=true"/>
    </RefParameter>
    <RefParameter Comment="X-NUCLEO-53L4A1 BSP drivers" DefaultValue="false" Group="Software component selection" Name="BoardOoExtensionJj53L4A1" TabName="BoardOoExtensionJj53L4A1" Type="boolean" Visible="false"/>
    <RefParameter Comment="VL53L3CX Component Driver" DefaultValue="false" Group="Software component selection" Name="BoardOoPartJjRangingJjVL53L3CX" TabName="BoardOoPartJjRanging" Type="boolean" Visible="false">
        <PossibleValue Comment="ENABLE" Semaphore="SEMBoardOoPartJjRangingJjVL53L3CX" Value="true"/>
        <PossibleValue Comment="DISABLE" Value="false"/>
        <Condition Diagnostic="Cortex-M Device and board setup (VL53L3CX Driver)" Expression="CONDITIONIiVL53L3CXOoCondition=true"/>
    </RefParameter>
    <RefParameter Comment="VL53L3CX Component Driver" DefaultValue="false" Group="Software component selection" Name="BoardOoPartJjRangingJjVL53L3CX" TabName="BoardOoPartJjRanging" Type="boolean" Visible="false"/>
    <RefParameter Comment="VL53L5CX Component Driver" DefaultValue="false" Group="Software component selection" Name="BoardOoPartJjRangingJjVL53L5CX" TabName="BoardOoPartJjRanging" Type="boolean" Visible="false">
        <PossibleValue Comment="ENABLE" Semaphore="SEMBoardOoPartJjRangingJjVL53L5CX" Value="true"/>
        <PossibleValue Comment="DISABLE" Value="false"/>
        <Condition Diagnostic="Cortex-M Device and board setup (VL53L5CX Driver)" Expression="CONDITIONIiVL53L5CXOoCondition=true"/>
    </RefParameter>
    <RefParameter Comment="VL53L5CX Component Driver" DefaultValue="false" Group="Software component selection" Name="BoardOoPartJjRangingJjVL53L5CX" TabName="BoardOoPartJjRanging" Type="boolean" Visible="false"/>
    <RefParameter Comment="VL53L7CX Component Driver" DefaultValue="false" Group="Software component selection" Name="BoardOoPartJjRangingJjVL53L7CX" TabName="BoardOoPartJjRanging" Type="boolean" Visible="false">
        <PossibleValue Comment="ENABLE" Semaphore="SEMBoardOoPartJjRangingJjVL53L7CX" Value="true"/>
        <PossibleValue Comment="DISABLE" Value="false"/>
        <Condition Diagnostic="Cortex-M Device and board setup (VL53L7CX Driver)" Expression="CONDITIONIiVL53L7CXOoCondition=true"/>
    </RefParameter>
    <RefParameter Comment="VL53L7CX Component Driver" DefaultValue="false" Group="Software component selection" Name="BoardOoPartJjRangingJjVL53L7CX" TabName="BoardOoPartJjRanging" Type="boolean" Visible="false"/>
    <RefParameter Comment="VL53L8CX Component Driver" DefaultValue="false" Group="Software component selection" Name="BoardOoPartJjRangingJjVL53L8CX" TabName="BoardOoPartJjRanging" Type="boolean" Visible="false">
        <PossibleValue Comment="ENABLE" Semaphore="SEMBoardOoPartJjRangingJjVL53L8CX" Value="true"/>
        <PossibleValue Comment="DISABLE" Value="false"/>
        <Condition Diagnostic="Cortex-M Device and board setup (VL53L8CX Driver)" Expression="CONDITIONIiVL53L8CXOoCondition=true"/>
    </RefParameter>
    <RefParameter Comment="VL53L8CX Component Driver" DefaultValue="false" Group="Software component selection" Name="BoardOoPartJjRangingJjVL53L8CX" TabName="BoardOoPartJjRanging" Type="boolean" Visible="false"/>
    <RefParameter Comment="VL53L1CB Component Driver" DefaultValue="false" Group="Software component selection" Name="BoardOoPartJjRangingJjVL53L1CB" TabName="BoardOoPartJjRanging" Type="boolean" Visible="false">
        <PossibleValue Comment="ENABLE" Semaphore="SEMBoardOoPartJjRangingJjVL53L1CB" Value="true"/>
        <PossibleValue Comment="DISABLE" Value="false"/>
        <Condition Diagnostic="Cortex-M Device and board setup (VL53L1CB Driver)" Expression="CONDITIONIiVL53L1CBOoCondition=true"/>
    </RefParameter>
    <RefParameter Comment="VL53L1CB Component Driver" DefaultValue="false" Group="Software component selection" Name="BoardOoPartJjRangingJjVL53L1CB" TabName="BoardOoPartJjRanging" Type="boolean" Visible="false"/>
    <RefParameter Comment="VL53L4CX Component Driver" DefaultValue="false" Group="Software component selection" Name="BoardOoPartJjRangingJjVL53L4CX" TabName="BoardOoPartJjRanging" Type="boolean" Visible="false">
        <PossibleValue Comment="ENABLE" Semaphore="SEMBoardOoPartJjRangingJjVL53L4CX" Value="true"/>
        <PossibleValue Comment="DISABLE" Value="false"/>
        <Condition Diagnostic="Cortex-M Device and board setup (VL53L4CX Driver)" Expression="CONDITIONIiVL53L4CXOoCondition=true"/>
    </RefParameter>
    <RefParameter Comment="VL53L4CX Component Driver" DefaultValue="false" Group="Software component selection" Name="BoardOoPartJjRangingJjVL53L4CX" TabName="BoardOoPartJjRanging" Type="boolean" Visible="false"/>
    <RefParameter Comment="VL53L4CD Component Driver" DefaultValue="false" Group="Software component selection" Name="BoardOoPartJjRangingJjVL53L4CD" TabName="BoardOoPartJjRanging" Type="boolean" Visible="false">
        <PossibleValue Comment="ENABLE" Semaphore="SEMBoardOoPartJjRangingJjVL53L4CD" Value="true"/>
        <PossibleValue Comment="DISABLE" Value="false"/>
        <Condition Diagnostic="Cortex-M Device and board setup (VL53L4CD Driver)" Expression="CONDITIONIiVL53L4CDOoCondition=true"/>
    </RefParameter>
    <RefParameter Comment="VL53L4CD Component Driver" DefaultValue="false" Group="Software component selection" Name="BoardOoPartJjRangingJjVL53L4CD" TabName="BoardOoPartJjRanging" Type="boolean" Visible="false"/>
    <RefParameter Comment="Device Application" DefaultValue="disable" Group="Software component selection" Name="TOF1IiApplicationsCcDeviceJjApplication" TabName="DeviceJjTOF1IiApplications" Type="list" Visible="false">
        <PossibleValue Comment="DISABLE" Value="DISABLE"/>
        <PossibleValue Comment="Simple ranging sample application for X-NUCLEO-53L4A1" Semaphore="SEMTOF1IiApplicationsCcDeviceJjApplicationJj53L4A1IiSimpleRanging" Value="53L4A1IiSimpleRanging"/>
        <PossibleValue Comment="Multi sensor ranging sample application for X-NUCLEO-53L4A1" Semaphore="SEMTOF1IiApplicationsCcDeviceJjApplicationJj53L4A1IiMultiSensorRanging" Value="53L4A1IiMultiSensorRanging"/>
        <PossibleValue Comment="Threshold detection sample application for X-NUCLEO-53L4A1" Semaphore="SEMTOF1IiApplicationsCcDeviceJjApplicationJj53L4A1IiThresholdDetection" Value="53L4A1IiThresholdDetection"/>
        <PossibleValue Comment="Simple Ranging example for VL53L4CD" Semaphore="SEMTOF1IiApplicationsCcDeviceJjApplicationJjVL53L4CDIiSimpleRanging" Value="VL53L4CDIiSimpleRanging"/>
        <PossibleValue Comment="Simple ranging sample application for X-NUCLEO-53L4A2" Semaphore="SEMTOF1IiApplicationsCcDeviceJjApplicationJj53L4A2IiSimpleRanging" Value="53L4A2IiSimpleRanging"/>
        <PossibleValue Comment="Multi sensor ranging sample application for X-NUCLEO-53L4A2" Semaphore="SEMTOF1IiApplicationsCcDeviceJjApplicationJj53L4A2IiMultiSensorRanging" Value="53L4A2IiMultiSensorRanging"/>
        <PossibleValue Comment="Simple Ranging example for VL53L4CX" Semaphore="SEMTOF1IiApplicationsCcDeviceJjApplicationJjVL53L4CXIiSimpleRanging" Value="VL53L4CXIiSimpleRanging"/>
        <PossibleValue Comment="Simple ranging sample application for X-NUCLEO-53L3A2" Semaphore="SEMTOF1IiApplicationsCcDeviceJjApplicationJj53L3A2IiSimpleRanging" Value="53L3A2IiSimpleRanging"/>
        <PossibleValue Comment="Multi sensor ranging sample application for X-NUCLEO-53L3A2" Semaphore="SEMTOF1IiApplicationsCcDeviceJjApplicationJj53L3A2IiMultiSensorRanging" Value="53L3A2IiMultiSensorRanging"/>
        <PossibleValue Comment="Simple Ranging example for VL53L3CX" Semaphore="SEMTOF1IiApplicationsCcDeviceJjApplicationJjVL53L3CXIiSimpleRanging" Value="VL53L3CXIiSimpleRanging"/>
        <PossibleValue Comment="Simple ranging sample application for X-NUCLEO-53L5A1" Semaphore="SEMTOF1IiApplicationsCcDeviceJjApplicationJj53L5A1IiSimpleRanging" Value="53L5A1IiSimpleRanging"/>
        <PossibleValue Comment="Multi sensor ranging sample application for X-NUCLEO-53L5A1" Semaphore="SEMTOF1IiApplicationsCcDeviceJjApplicationJj53L5A1IiMultiSensorRanging" Value="53L5A1IiMultiSensorRanging"/>
        <PossibleValue Comment="Threshold detection sample application for X-NUCLEO-53L5A1" Semaphore="SEMTOF1IiApplicationsCcDeviceJjApplicationJj53L5A1IiThresholdDetection" Value="53L5A1IiThresholdDetection"/>
        <PossibleValue Comment="Simple Ranging example for VL53L5CX" Semaphore="SEMTOF1IiApplicationsCcDeviceJjApplicationJjVL53L5CXIiSimpleRanging" Value="VL53L5CXIiSimpleRanging"/>
        <PossibleValue Comment="Simple ranging sample application for X-NUCLEO-53L7A1" Semaphore="SEMTOF1IiApplicationsCcDeviceJjApplicationJj53L7A1IiSimpleRanging" Value="53L7A1IiSimpleRanging"/>
        <PossibleValue Comment="Multi sensor ranging sample application for X-NUCLEO-53L7A1" Semaphore="SEMTOF1IiApplicationsCcDeviceJjApplicationJj53L7A1IiMultiSensorRanging" Value="53L7A1IiMultiSensorRanging"/>
        <PossibleValue Comment="Threshold detection sample application for X-NUCLEO-53L7A1" Semaphore="SEMTOF1IiApplicationsCcDeviceJjApplicationJj53L7A1IiThresholdDetection" Value="53L7A1IiThresholdDetection"/>
        <PossibleValue Comment="Simple Ranging example for VL53L7CX" Semaphore="SEMTOF1IiApplicationsCcDeviceJjApplicationJjVL53L7CXIiSimpleRanging" Value="VL53L7CXIiSimpleRanging"/>
        <PossibleValue Comment="Simple ranging sample application for X-NUCLEO-53L8A1" Semaphore="SEMTOF1IiApplicationsCcDeviceJjApplicationJj53L8A1IiSimpleRanging" Value="53L8A1IiSimpleRanging"/>
        <PossibleValue Comment="Threshold detection sample application for X-NUCLEO-53L8A1" Semaphore="SEMTOF1IiApplicationsCcDeviceJjApplicationJj53L8A1IiThresholdDetection" Value="53L8A1IiThresholdDetection"/>
        <PossibleValue Comment="Simple Ranging example for VL53L8CX" Semaphore="SEMTOF1IiApplicationsCcDeviceJjApplicationJjVL53L8CXIiSimpleRanging" Value="VL53L8CXIiSimpleRanging"/>
        <PossibleValue Comment="Simple ranging sample application for X-NUCLEO-53L1A2" Semaphore="SEMTOF1IiApplicationsCcDeviceJjApplicationJj53L1A2IiSimpleRanging" Value="53L1A2IiSimpleRanging"/>
        <PossibleValue Comment="Multi sensor ranging sample application for X-NUCLEO-53L1A2" Semaphore="SEMTOF1IiApplicationsCcDeviceJjApplicationJj53L1A2IiMultiSensorRanging" Value="53L1A2IiMultiSensorRanging"/>
        <PossibleValue Comment="Simple Ranging example for VL53L1CB" Semaphore="SEMTOF1IiApplicationsCcDeviceJjApplicationJjVL53L1CBIiSimpleRanging" Value="VL53L1CBIiSimpleRanging"/>
    </RefParameter>
    <RefParameter Comment="BSP for Ranging Sensor" DefaultValue="false" Group="Software component selection" Name="STM32CubeIiCustomIiBSPIiDriversCcBoardOoSupportJjCustomJjRANGINGIiSENSOR" TabName="BoardOoSupportJjSTM32CubeIiCustomIiBSPIiDrivers" Type="boolean" Visible="false">
        <PossibleValue Comment="ENABLE" Semaphore="SEMSTM32CubeIiCustomIiBSPIiDriversCcBoardOoSupportJjCustomJjRANGINGIiSENSOR" Value="true"/>
        <PossibleValue Comment="DISABLE" Value="false"/>
    </RefParameter>
    <RefParameter Comment="Condition Ii Cortex Aa M Oo Device" DefaultValue="true" Name="CONDITIONIiCortexAaMOoDevice" Type="boolean" Visible="false"/>
    <RefParameter Comment="Condition Ii Cm3 Ii Keil" DefaultValue="true" Name="CONDITIONIiCM3IiKeil" Type="boolean" Visible="false"/>
    <RefParameter Comment="Condition Ii53 L5 A1 Oo Examples Oo Condition" DefaultValue="true" Name="CONDITIONIi53L5A1OoExamplesOoCondition" Type="boolean" Visible="false"/>
    <RefParameter Comment="Condition Ii Cm3 Ii Gcc" DefaultValue="true" Name="CONDITIONIiCM3IiGCC" Type="boolean" Visible="false"/>
    <RefParameter Comment="Condition Ii Deny Ooall Ooboards Oobut Oo X Aa Nucleo Aa53 L1 A2" DefaultValue="true" Name="CONDITIONIiDenyOoallOoboardsOobutOoXAaNUCLEOAa53L1A2" Type="boolean" Visible="false"/>
    <RefParameter Comment="Condition Ii Exclude Oocustom Oo Tof Oo Bsp" DefaultValue="true" Name="CONDITIONIiExcludeOocustomOoTOFOoBSP" Type="boolean" Visible="false"/>
    <RefParameter Comment="Condition Ii53 L4 A1 Oo Examples Oo Condition" DefaultValue="true" Name="CONDITIONIi53L4A1OoExamplesOoCondition" Type="boolean" Visible="false"/>
    <RefParameter Comment="Condition Ii Cm33 Ii Keil" DefaultValue="true" Name="CONDITIONIiCM33IiKeil" Type="boolean" Visible="false"/>
    <RefParameter Comment="Condition Ii Deny Ooall Ooboards Oobut Oo X Aa Nucleo Aa53 L5 A1" DefaultValue="true" Name="CONDITIONIiDenyOoallOoboardsOobutOoXAaNUCLEOAa53L5A1" Type="boolean" Visible="false"/>
    <RefParameter Comment="Condition Ii Deny Ooall Ooboards Oobut Oo X Aa Nucleo Aa53 L3 A2" DefaultValue="true" Name="CONDITIONIiDenyOoallOoboardsOobutOoXAaNUCLEOAa53L3A2" Type="boolean" Visible="false"/>
    <RefParameter Comment="Condition Ii Exclude Oo Applications Oofor Oo53 L1 A2" DefaultValue="true" Name="CONDITIONIiExcludeOoApplicationsOoforOo53L1A2" Type="boolean" Visible="false"/>
    <RefParameter Comment="Condition Ii Exclude Oo All Oo Satellites Oobut Oo Vl53 L4 Cx" DefaultValue="true" Name="CONDITIONIiExcludeOoALLOoSATELLITESOobutOoVL53L4CX" Type="boolean" Visible="false"/>
    <RefParameter Comment="Condition Ii Deny Ooall Ooboards Oobut Oo X Aa Nucleo Aa53 L7 A1" DefaultValue="true" Name="CONDITIONIiDenyOoallOoboardsOobutOoXAaNUCLEOAa53L7A1" Type="boolean" Visible="false"/>
    <RefParameter Comment="Condition Ii Exclude Oo All Oo Satellites Oobut Oo Vl53 L8 Cx" DefaultValue="true" Name="CONDITIONIiExcludeOoALLOoSATELLITESOobutOoVL53L8CX" Type="boolean" Visible="false"/>
    <RefParameter Comment="Condition Ii Cm4 Ii Gcc" DefaultValue="true" Name="CONDITIONIiCM4IiGCC" Type="boolean" Visible="false"/>
    <RefParameter Comment="Condition Ii Exclude Oo Applications Oofor Oo53 L7 A1" DefaultValue="true" Name="CONDITIONIiExcludeOoApplicationsOoforOo53L7A1" Type="boolean" Visible="false"/>
    <RefParameter Comment="Condition Ii Exclude Oo Applications Oofor Oo53 L3 A2" DefaultValue="true" Name="CONDITIONIiExcludeOoApplicationsOoforOo53L3A2" Type="boolean" Visible="false"/>
    <RefParameter Comment="Condition Ii Exclude Oo Applications Oofor Oo53 L5 A1" DefaultValue="true" Name="CONDITIONIiExcludeOoApplicationsOoforOo53L5A1" Type="boolean" Visible="false"/>
    <RefParameter Comment="Condition Ii Vl53 L3 Cx Oo Hw Oo Condition" DefaultValue="true" Name="CONDITIONIiVL53L3CXOoHWOoCondition" Type="boolean" Visible="false"/>
    <RefParameter Comment="Condition Ii Exclude Oo Nucleo Oo Applications Oobut Oo53 L5 A1" DefaultValue="true" Name="CONDITIONIiExcludeOoNUCLEOOoApplicationsOobutOo53L5A1" Type="boolean" Visible="false"/>
    <RefParameter Comment="Condition Ii Exclude Oo Nucleo Oo Applications Oobut Oo53 L3 A2" DefaultValue="true" Name="CONDITIONIiExcludeOoNUCLEOOoApplicationsOobutOo53L3A2" Type="boolean" Visible="false"/>
    <RefParameter Comment="Condition Ii Exclude Oo Nucleo Oo Applications Oobut Oo53 L1 A2" DefaultValue="true" Name="CONDITIONIiExcludeOoNUCLEOOoApplicationsOobutOo53L1A2" Type="boolean" Visible="false"/>
    <RefParameter Comment="Condition Ii Cm3 Ii Iar" DefaultValue="true" Name="CONDITIONIiCM3IiIAR" Type="boolean" Visible="false"/>
    <RefParameter Comment="Condition Ii Exclude Oo Nucleo Oo Applications Oobut Oo53 L7 A1" DefaultValue="true" Name="CONDITIONIiExcludeOoNUCLEOOoApplicationsOobutOo53L7A1" Type="boolean" Visible="false"/>
    <RefParameter Comment="Condition Ii Cm4 Ii Iar" DefaultValue="true" Name="CONDITIONIiCM4IiIAR" Type="boolean" Visible="false"/>
    <RefParameter Comment="Condition Ii Vl53 L8 Cx Oo Hw Oo Condition" DefaultValue="true" Name="CONDITIONIiVL53L8CXOoHWOoCondition" Type="boolean" Visible="false"/>
    <RefParameter Comment="Condition Ii Cm0 Hh Ii Gcc" DefaultValue="true" Name="CONDITIONIiCM0HhIiGCC" Type="boolean" Visible="false"/>
    <RefParameter Comment="Condition Ii Vl53 L1 Cb Oo Condition" DefaultValue="true" Name="CONDITIONIiVL53L1CBOoCondition" Type="boolean" Visible="false"/>
    <RefParameter Comment="Condition Ii Ranging Ii Sensor Oo Condition" DefaultValue="true" Name="CONDITIONIiRANGINGIiSENSOROoCondition" Type="boolean" Visible="false"/>
    <RefParameter Comment="Condition Ii Exclude Oo All Oo Satellites Oobut Oo Vl53 L4 Cd" DefaultValue="true" Name="CONDITIONIiExcludeOoALLOoSATELLITESOobutOoVL53L4CD" Type="boolean" Visible="false"/>
    <RefParameter Comment="Condition Ii Cm0 Hh Ii Keil" DefaultValue="true" Name="CONDITIONIiCM0HhIiKeil" Type="boolean" Visible="false"/>
    <RefParameter Comment="Condition Ii53 L8 A1 Oo Examples Oo Condition" DefaultValue="true" Name="CONDITIONIi53L8A1OoExamplesOoCondition" Type="boolean" Visible="false"/>
    <RefParameter Comment="Condition Ii53 L1 A2 Oo Examples Oo Condition" DefaultValue="true" Name="CONDITIONIi53L1A2OoExamplesOoCondition" Type="boolean" Visible="false"/>
    <RefParameter Comment="Condition Ii Cm0 Hh Ii Iar" DefaultValue="true" Name="CONDITIONIiCM0HhIiIAR" Type="boolean" Visible="false"/>
    <RefParameter Comment="Condition Ii Cm33 Ii Gcc" DefaultValue="true" Name="CONDITIONIiCM33IiGCC" Type="boolean" Visible="false"/>
    <RefParameter Comment="Condition Ii Cm0 Ii Keil" DefaultValue="true" Name="CONDITIONIiCM0IiKeil" Type="boolean" Visible="false"/>
    <RefParameter Comment="Condition Ii53 L7 A1 Oo Examples Oo Condition" DefaultValue="true" Name="CONDITIONIi53L7A1OoExamplesOoCondition" Type="boolean" Visible="false"/>
    <RefParameter Comment="Condition Ii53 L1 A2 Oo Condition" DefaultValue="true" Name="CONDITIONIi53L1A2OoCondition" Type="boolean" Visible="false"/>
    <RefParameter Comment="Condition Ii Vl53 L4 Cd Oo Hw Oo Condition" DefaultValue="true" Name="CONDITIONIiVL53L4CDOoHWOoCondition" Type="boolean" Visible="false"/>
    <RefParameter Comment="Condition Ii Cm7 Ii Iar" DefaultValue="true" Name="CONDITIONIiCM7IiIAR" Type="boolean" Visible="false"/>
    <RefParameter Comment="Condition Ii Exclude Oo Applications Oofor Oo53 L8 A1" DefaultValue="true" Name="CONDITIONIiExcludeOoApplicationsOoforOo53L8A1" Type="boolean" Visible="false"/>
    <RefParameter Comment="Condition Ii53 L4 A2 Oo Examples Oo Condition" DefaultValue="true" Name="CONDITIONIi53L4A2OoExamplesOoCondition" Type="boolean" Visible="false"/>
    <RefParameter Comment="Condition Ii Deny Ooall Ooboards Oobut Oo X Aa Nucleo Aa53 L4 A2" DefaultValue="true" Name="CONDITIONIiDenyOoallOoboardsOobutOoXAaNUCLEOAa53L4A2" Type="boolean" Visible="false"/>
    <RefParameter Comment="Condition Ii Deny Ooall Ooboards Oobut Oo X Aa Nucleo Aa53 L4 A1" DefaultValue="true" Name="CONDITIONIiDenyOoallOoboardsOobutOoXAaNUCLEOAa53L4A1" Type="boolean" Visible="false"/>
    <RefParameter Comment="Condition Ii Cm0 Ii Gcc" DefaultValue="true" Name="CONDITIONIiCM0IiGCC" Type="boolean" Visible="false"/>
    <RefParameter Comment="Condition Ii Exclude Oo All Oo Satellites Oobut Oo Vl53 L3 Cx" DefaultValue="true" Name="CONDITIONIiExcludeOoALLOoSATELLITESOobutOoVL53L3CX" Type="boolean" Visible="false"/>
    <RefParameter Comment="Condition Ii Vl53 L7 Cx Oo Hw Oo Condition" DefaultValue="true" Name="CONDITIONIiVL53L7CXOoHWOoCondition" Type="boolean" Visible="false"/>
    <RefParameter Comment="Condition Ii Deny Ooall Ooboards Oobut Oo X Aa Nucleo Aa53 L8 A1" DefaultValue="true" Name="CONDITIONIiDenyOoallOoboardsOobutOoXAaNUCLEOAa53L8A1" Type="boolean" Visible="false"/>
    <RefParameter Comment="Condition Ii53 L3 A2 Oo Condition" DefaultValue="true" Name="CONDITIONIi53L3A2OoCondition" Type="boolean" Visible="false"/>
    <RefParameter Comment="Condition Ii Exclude Oo All Oo Satellites Oobut Oo Vl53 L7 Cx" DefaultValue="true" Name="CONDITIONIiExcludeOoALLOoSATELLITESOobutOoVL53L7CX" Type="boolean" Visible="false"/>
    <RefParameter Comment="Condition Ii Exclude Oo Applications Oofor Oo53 L4 A1" DefaultValue="true" Name="CONDITIONIiExcludeOoApplicationsOoforOo53L4A1" Type="boolean" Visible="false"/>
    <RefParameter Comment="Condition Ii Exclude Oo Applications Oofor Oo53 L4 A2" DefaultValue="true" Name="CONDITIONIiExcludeOoApplicationsOoforOo53L4A2" Type="boolean" Visible="false"/>
    <RefParameter Comment="Condition Ii53 L4 A2 Oo Condition" DefaultValue="true" Name="CONDITIONIi53L4A2OoCondition" Type="boolean" Visible="false"/>
    <RefParameter Comment="Condition Ii Exclude Oo All Oo Satellites Oobut Oo Vl53 L5 Cx" DefaultValue="true" Name="CONDITIONIiExcludeOoALLOoSATELLITESOobutOoVL53L5CX" Type="boolean" Visible="false"/>
    <RefParameter Comment="Condition Ii Vl53 L1 Cb Oo Hw Oo Condition" DefaultValue="true" Name="CONDITIONIiVL53L1CBOoHWOoCondition" Type="boolean" Visible="false"/>
    <RefParameter Comment="Condition Ii53 L8 A1 Oo Condition" DefaultValue="true" Name="CONDITIONIi53L8A1OoCondition" Type="boolean" Visible="false"/>
    <RefParameter Comment="Condition Ii Exclude Oo Nucleo Oo Applications Oobut Oo53 L4 A2" DefaultValue="true" Name="CONDITIONIiExcludeOoNUCLEOOoApplicationsOobutOo53L4A2" Type="boolean" Visible="false"/>
    <RefParameter Comment="Condition Ii Ranging Ii Sensor" DefaultValue="true" Name="CONDITIONIiRANGINGIiSENSOR" Type="boolean" Visible="false"/>
    <RefParameter Comment="Condition Ii Exclude Oo Nucleo Oo Applications Oobut Oo53 L4 A1" DefaultValue="true" Name="CONDITIONIiExcludeOoNUCLEOOoApplicationsOobutOo53L4A1" Type="boolean" Visible="false"/>
    <RefParameter Comment="Condition Ii Exclude Oo Nucleo Oo Applications Oobut Oo53 L8 A1" DefaultValue="true" Name="CONDITIONIiExcludeOoNUCLEOOoApplicationsOobutOo53L8A1" Type="boolean" Visible="false"/>
    <RefParameter Comment="Condition Ii53 L7 A1 Oo Condition" DefaultValue="true" Name="CONDITIONIi53L7A1OoCondition" Type="boolean" Visible="false"/>
    <RefParameter Comment="Condition Ii Cm7 Ii Keil" DefaultValue="true" Name="CONDITIONIiCM7IiKeil" Type="boolean" Visible="false"/>
    <RefParameter Comment="Condition Ii Cm7 Ii Gcc" DefaultValue="true" Name="CONDITIONIiCM7IiGCC" Type="boolean" Visible="false"/>
    <RefParameter Comment="Condition Ii Vl53 L4 Cd Oo Condition" DefaultValue="true" Name="CONDITIONIiVL53L4CDOoCondition" Type="boolean" Visible="false"/>
    <RefParameter Comment="Condition Ii Vl53 L4 Cx Oo Hw Oo Condition" DefaultValue="true" Name="CONDITIONIiVL53L4CXOoHWOoCondition" Type="boolean" Visible="false"/>
    <RefParameter Comment="Condition Ii Vl53 L8 Cx Oo Condition" DefaultValue="true" Name="CONDITIONIiVL53L8CXOoCondition" Type="boolean" Visible="false"/>
    <RefParameter Comment="Condition Ii Vl53 L5 Cx Oo Hw Oo Condition" DefaultValue="true" Name="CONDITIONIiVL53L5CXOoHWOoCondition" Type="boolean" Visible="false"/>
    <RefParameter Comment="Condition Ii Exclude Oo All Oo Satellites Oobut Oo Vl53 L1 Cb" DefaultValue="true" Name="CONDITIONIiExcludeOoALLOoSATELLITESOobutOoVL53L1CB" Type="boolean" Visible="false"/>
    <RefParameter Comment="Condition Ii Vl53 L7 Cx Oo Condition" DefaultValue="true" Name="CONDITIONIiVL53L7CXOoCondition" Type="boolean" Visible="false"/>
    <RefParameter Comment="Condition Ii53 L3 A2 Oo Examples Oo Condition" DefaultValue="true" Name="CONDITIONIi53L3A2OoExamplesOoCondition" Type="boolean" Visible="false"/>
    <RefParameter Comment="Condition Ii Cm33 Ii Iar" DefaultValue="true" Name="CONDITIONIiCM33IiIAR" Type="boolean" Visible="false"/>
    <RefParameter Comment="Condition Ii Cm0 Ii Iar" DefaultValue="true" Name="CONDITIONIiCM0IiIAR" Type="boolean" Visible="false"/>
    <RefParameter Comment="Condition Ii Deny Oo All Oo Board Ooextensions" DefaultValue="true" Name="CONDITIONIiDenyOoAllOoBoardOoextensions" Type="boolean" Visible="false"/>
    <RefParameter Comment="Condition Ii Exclude Oo All Oo Nucleo Oo Applications" DefaultValue="true" Name="CONDITIONIiExcludeOoAllOoNUCLEOOoApplications" Type="boolean" Visible="false"/>
    <RefParameter Comment="Condition Ii53 L4 A1 Oo Condition" DefaultValue="true" Name="CONDITIONIi53L4A1OoCondition" Type="boolean" Visible="false"/>
    <RefParameter Comment="Condition Ii Cm4 Ii Keil" DefaultValue="true" Name="CONDITIONIiCM4IiKeil" Type="boolean" Visible="false"/>
    <RefParameter Comment="Condition Ii Vl53 L3 Cx Oo Condition" DefaultValue="true" Name="CONDITIONIiVL53L3CXOoCondition" Type="boolean" Visible="false"/>
    <RefParameter Comment="Condition Ii Vl53 L5 Cx Oo Condition" DefaultValue="true" Name="CONDITIONIiVL53L5CXOoCondition" Type="boolean" Visible="false"/>
    <RefParameter Comment="Condition Ii Exclude Oocustom Oo Tof Oocomponents" DefaultValue="true" Name="CONDITIONIiExcludeOocustomOoTOFOocomponents" Type="boolean" Visible="false"/>
    <RefParameter Comment="Condition Ii53 L5 A1 Oo Condition" DefaultValue="true" Name="CONDITIONIi53L5A1OoCondition" Type="boolean" Visible="false"/>
    <RefParameter Comment="Condition Ii Vl53 L4 Cx Oo Condition" DefaultValue="true" Name="CONDITIONIiVL53L4CXOoCondition" Type="boolean" Visible="false"/>
    <RefParameter Added="true" Comment="Ranging Mode" DefaultValue="Polling" Group="Basic Parameters" Name="TOF_RANGING_MODE" TabName="Parameter Settings" Type="list">
        <Description>Polling or Interrupt</Description>
        <PossibleValue Comment="Interrupt" Value="Interrupt"/>
        <PossibleValue Comment="Polling" Value="Polling"/>
    </RefParameter>
    <RefParameter Added="true" Comment="Offset Calibration" DefaultValue="No" Group="Basic Parameters" Name="TOF_OFFSET_CALIBRATION" TabName="Parameter Settings" Type="list">
        <Description>When enabled, the application performs an offset calibration before starting the ranging (more details in the user manual)</Description>
        <PossibleValue Comment="Yes" Value="Yes"/>
        <PossibleValue Comment="No" Value="No"/>
    </RefParameter>
    <RefParameter Added="true" Comment="Xtalk Calibration" DefaultValue="No" Group="Basic Parameters" Name="TOF_XTALK_CALIBRATION" TabName="Parameter Settings" Type="list">
        <Description>When enabled, the application performs a xtalk calibration before starting the ranging (more details in the user manual)</Description>
        <PossibleValue Comment="Yes" Value="Yes"/>
        <PossibleValue Comment="No" Value="No"/>
    </RefParameter>
</IP>
